emantomo/__init__.py
emantomo/bibtex.py
emantomo/constants.py
emantomo/e2converter.py
emantomo/e2ih.py
emantomo/eman2_logo.png
emantomo/objects.py
emantomo/protocols.conf
emantomo/utils.py
emantomo/wizards.py
emantomo/convert/__init__.py
emantomo/convert/convert.py
emantomo/convert/dataimport.py
emantomo/convert/lstConvert.py
emantomo/protocols/__init__.py
emantomo/protocols/protocol_average_subtomos.py
emantomo/protocols/protocol_base.py
emantomo/protocols/protocol_clip_tomograms.py
emantomo/protocols/protocol_estimate_ctf.py
emantomo/protocols/protocol_extraction_from_tomo.py
emantomo/protocols/protocol_extraction_from_ts.py
emantomo/protocols/protocol_initialmodel_new.py
emantomo/protocols/protocol_refine_multi_new.py
emantomo/protocols/protocol_refine_new.py
emantomo/protocols/protocol_refine_new_base.py
emantomo/protocols/protocol_template_matching.py
emantomo/protocols/protocol_tomo_boxing.py
emantomo/protocols/protocol_tomo_boxing_convnet.py
emantomo/protocols/protocol_tomo_fill_mw.py
emantomo/protocols/protocol_tomo_initialmodel.py
emantomo/protocols/protocol_tomo_subtomogram_refinement.py
emantomo/protocols/protocol_ts_align_and_tomo_rec.py
emantomo/protocols/deprecated_20230914/__init__.py
emantomo/protocols/deprecated_20230914/protocol_mra_refinement.py
emantomo/protocols/deprecated_20230914/protocol_pca_kmeans_classify_subtomos.py
emantomo/protocols/deprecated_20230914/protocol_tomo_tilt_refine.py
emantomo/templates/2023_12_emantomo_sta_tutorial_workflow.json.template
emantomo/tests/__init__.py
emantomo/tests/test_eman_sta_classic_base.py
emantomo/tests/test_protocols_other_functionalities.py
emantomo/tests/test_protocols_sta_classic_emantomoextraction.py
emantomo/tests/test_protocols_sta_classic_workflow.py
emantomo/tests/test_protocols_sta_pppt.py
emantomo/viewers/__init__.py
emantomo/viewers/tomoPovider.py
emantomo/viewers/viewers_data.py
emantomo/viewers/views_tkinter_tree.py
scipion_em_emantomo-3.3.5.dist-info/LICENSE
scipion_em_emantomo-3.3.5.dist-info/METADATA
scipion_em_emantomo-3.3.5.dist-info/WHEEL
scipion_em_emantomo-3.3.5.dist-info/entry_points.txt
scipion_em_emantomo-3.3.5.dist-info/top_level.txt
scipion_em_emantomo-3.3.5.dist-info/RECORD
