Metadata-Version: 2.1
Name: scipion-em-emantomo
Version: 3.3.5
Summary: Plugin to use EMAN2 tomography programs within the Scipion framework
Home-page: https://github.com/scipion-em/scipion-em-emantomo
Author: I2PC
Author-email: scipion@cnb.csic.es
License: UNKNOWN
Project-URL: Bug Reports, https://github.com/scipion-em/scipion-em-emantomo/issues
Project-URL: Source, https://github.com/scipion-em/scipion-em-emantomo/
Keywords: scipion electron-microscopy cryo-em structural-biology image-processing scipion-3.0 tomography
Platform: UNKNOWN
Classifier: Development Status :: 4 - Beta
Classifier: License :: OSI Approved :: GNU General Public License v3 (GPLv3)
Classifier: Programming Language :: Python :: 3
Requires-Dist: scipion-em>=3.5.0
Requires-Dist: scipion-em-eman2
Requires-Dist: scipion-em-tomo>=3.7.0
Requires-Dist: h5py==3.8.0
